is_bimodal-0.2.1.dist-info/METADATA
is_bimodal-0.2.1.dist-info/WHEEL
is_bimodal/__init__.py
is_bimodal/is_bimodal.cpython-39-aarch64-linux-gnu.so
is_bimodal-0.2.1.dist-info/RECORD
